{
    "defaultSeverity": "warning",
    "extends": [
        "tslint:recommended"
    ],
    "rules": {
        "arrow-parens": [true, "ban-single-arg-parens"],
        "indent": [
            true,
            "spaces",
            2
        ],
        "interface-name": [true, "never-prefix"],
        "member-access": [true, "no-public"],
        "member-ordering": [
            true,
            {
                "order": [
                    "private-static-field",
                    "private-static-method",
                    "private-instance-field",
                    "private-constructor",
                    "private-instance-method",

                    "protected-static-field",
                    "protected-static-method",
                    "protected-instance-field",
                    "protected-constructor",
                    "protected-instance-method",

                    "public-static-field",
                    "public-static-method",
                    "public-instance-field",
                    "public-constructor",
                    "public-instance-method"
                ]
            }
        ],
        "newline-before-return": true,
        "no-consecutive-blank-lines": true,
        "number-literal-format": true,
        "quotemark": [
            true,
            "single"
        ],
        "variable-name": {
            "options": [
              "check-format",
              "allow-leading-underscore"
            ]
        }
    }
}